{"Objs": [{"!Parameters": {"DropTable": "Normal", "SharpWeaponJudgeType": 0}, "HashId": 120304873, "Rotate": 1.5707963705062866, "SRTHash": 264709019, "Translate": [-24.0, 0.0, 8.0], "UnitConfigName": "DgnObj_Hrl_Box4x4x6_03"}, {"!Parameters": {"DropTable": "Normal", "SharpWeaponJudgeType": 0}, "HashId": 177569681, "Rotate": 1.5707963705062866, "SRTHash": 1027264208, "Translate": [28.0, 0.0, -18.0], "UnitConfigName": "DgnObj_Hrl_Box4x8x12_01"}, {"!Parameters": {"DropTable": "Normal", "SharpWeaponJudgeType": 0}, "HashId": 187033558, "Rotate": 1.5707963705062866, "SRTHash": -1595286390, "Translate": [28.0, 0.0, -10.0], "UnitConfigName": "DgnObj_Hrl_Box4x8x12_01"}, {"!Parameters": {"DropTable": "Normal", "SharpWeaponJudgeType": 0}, "HashId": 231047088, "OnlyOne": true, "SRTHash": -1067609467, "Translate": [0.0, 8.0, -32.099998474121094], "UnitConfigName": "DgnObj_Hrl_Box4x4Wainscot_02"}, {"!Parameters": {"DropTable": "Normal", "SharpWeaponJudgeType": 0}, "HashId": 254853540, "SRTHash": -100443639, "Translate": [11.0, 2.0, -31.219999313354492], "UnitConfigName": "DgnObj_Hrl_Box2x2Wainscot_01"}, {"!Parameters": {"DropTable": "Normal", "SharpWeaponJudgeType": 0}, "HashId": 276588539, "Rotate": 1.5707963705062866, "SRTHash": 632073278, "Translate": [4.0, 2.0, -12.0], "UnitConfigName": "DgnObj_Hrl_Box4x4x4_03"}, {"!Parameters": {"DropTable": "Normal", "SharpWeaponJudgeType": 0}, "HashId": 281038600, "SRTHash": -1452369234, "Translate": [-10.0, 2.0, -28.0], "UnitConfigName": "DgnObj_Hrl_TowerRoof2x2_A_01"}, {"HashId": 305525020, "SRTHash": -2050181218, "Translate": [0.0, 6.0, -0.5], "UnitConfigName": "DgnObj_Hrl_RoadEnd4x4_01"}, {"!Parameters": {"DropTable": "Normal", "SharpWeaponJudgeType": 0}, "HashId": 349530490, "Rotate": 1.5707963705062866, "SRTHash": 701516374, "Translate": [-24.0, 0.0, 16.0], "UnitConfigName": "DgnObj_Hrl_Box4x4x6_03"}, {"!Parameters": {"DropTable": "Normal", "SharpWeaponJudgeType": 0}, "HashId": 371251054, "Rotate": 1.5707963705062866, "SRTHash": 1792448605, "Translate": [-28.0, 0.0, -2.0], "UnitConfigName": "DgnObj_Hrl_Box4x8x12_01"}, {"!Parameters": {"DropTable": "Normal", "SharpWeaponJudgeType": 0}, "HashId": 392340935, "Rotate": -1.5707963705062866, "SRTHash": -18005042, "Translate": [24.0, 0.0, -24.0], "UnitConfigName": "DgnObj_Hrl_Box4x4x6_03"}, {"!Parameters": {"DropTable": "Normal", "SharpWeaponJudgeType": 0}, "HashId": 395333417, "SRTHash": 2108283874, "Translate": [-2.0, 6.0, -20.0], "UnitConfigName": "DgnObj_Hrl_Box4x4x2Top_01"}, {"!Parameters": {"DropTable": "Normal", "SharpWeaponJudgeType": 0}, "HashId": 405393579, "SRTHash": -1906973279, "Translate": [-4.5, 8.0, -15.0], "UnitConfigName": "DgnObj_Hrl_TowerRoof2x2_A_01"}, {"!Parameters": {"DropTable": "Normal", "SharpWeaponJudgeType": 0}, "HashId": 417020485, "SRTHash": 35539575, "Translate": [-8.0, 0.0, -26.0], "UnitConfigName": "DgnObj_hrl_Box8x8x2_01"}, {"!Parameters": {"DropTable": "Normal", "SharpWeaponJudgeType": 0}, "HashId": 439256145, "SRTHash": -856365542, "Translate": [-10.0, 2.0, 8.0], "UnitConfigName": "DgnObj_Hrl_TowerRoof4x4_A_01"}, {"!Parameters": {"DropTable": "Normal", "SharpWeaponJudgeType": 0}, "HashId": 483269687, "Rotate": -3.1415927410125732, "SRTHash": -1662843192, "Translate": [-1.0, 2.0, 31.0], "UnitConfigName": "DgnObj_Hrl_Box2x2Wainscot_02"}, {"!Parameters": {"DropTable": "Normal", "SharpWeaponJudgeType": 0}, "HashId": 499297411, "SRTHash": -651348918, "Translate": [-28.0, 12.0, 0.0], "UnitConfigName": "DgnObj_Hrl_TowerRoof4x4_A_01"}, {"HashId": 556291477, "SRTHash": -472018153, "Translate": [32.0, 12.0, -16.0], "UnitConfigName": "DgnObj_Hrl_BoxCover4x4_01"}, {"!Parameters": {"DropTable": "Normal", "SharpWeaponJudgeType": 0}, "HashId": 584145717, "Rotate": 1.5707963705062866, "SRTHash": 2047050237, "Translate": [-24.0, 0.0, -28.0], "UnitConfigName": "DgnObj_Hrl_Box4x4x6_03"}, {"!Parameters": {"DropTable": "Normal", "SharpWeaponJudgeType": 0}, "HashId": 624784359, "SRTHash": -1522330856, "Translate": [-2.0, 6.0, -28.0], "UnitConfigName": "DgnObj_Hrl_Box4x4x2Top_01"}, {"!Parameters": {"DropTable": "Normal", "SharpWeaponJudgeType": 0}, "HashId": 634362121, "SRTHash": -1454198633, "Translate": [-2.0, 0.0, -24.0], "UnitConfigName": "DgnObj_Hrl_Box4x4x6Under_01"}, {"!Parameters": {"DropTable": "Normal", "SharpWeaponJudgeType": 0}, "HashId": 667471347, "Rotate": 1.5707963705062866, "SRTHash": -692311377, "Translate": [-24.0, 0.0, 4.0], "UnitConfigName": "DgnObj_Hrl_Box4x4x6_03"}, {"!Parameters": {"DropTable": "Normal", "SharpWeaponJudgeType": 0}, "HashId": 691216600, "SRTHash": -30488644, "Translate": [28.0, 12.0, 24.0], "UnitConfigName": "DgnObj_Hrl_TowerRoof4x4_A_01"}, {"!Parameters": {"DropTable": "Normal", "SharpWeaponJudgeType": 0}, "HashId": 712377995, "Rotate": 1.5707963705062866, "SRTHash": 1749695461, "Translate": [-24.0, 0.0, -8.0], "UnitConfigName": "DgnObj_Hrl_Box4x4x6_03"}, {"!Parameters": {"DropTable": "Normal", "SharpWeaponJudgeType": 0}, "HashId": 713354341, "Rotate": 1.5707963705062866, "SRTHash": 1647112657, "Translate": [-24.0, 0.0, -24.0], "UnitConfigName": "DgnObj_Hrl_Box4x4x6_03"}, {"!Parameters": {"DropTable": "Normal", "SharpWeaponJudgeType": 0}, "HashId": 734437068, "SRTHash": -1158558609, "Translate": [-8.0, 0.0, -10.0], "UnitConfigName": "DgnObj_hrl_Box8x8x2_01"}, {"!Parameters": {"DropTable": "Normal", "SharpWeaponJudgeType": 0}, "HashId": 740996638, "Rotate": 1.5707963705062866, "SRTHash": -486155873, "Translate": [28.0, 0.0, -2.0], "UnitConfigName": "DgnObj_Hrl_Box4x8x12_01"}, {"!Parameters": {"DropTable": "Normal", "SharpWeaponJudgeType": 0}, "HashId": 757466794, "SRTHash": -1148954833, "Translate": [-11.0, 2.0, -31.0], "UnitConfigName": "DgnObj_Hrl_Box2x2Wainscot_01"}, {"!Parameters": {"DropTable": "Normal", "SharpWeaponJudgeType": 0}, "HashId": 761840823, "Rotate": 1.5707963705062866, "SRTHash": -767961526, "Translate": [6.0, 2.0, -24.0], "UnitConfigName": "DgnObj_Hrl_Box4x4x6_03"}, {"HashId": 802404542, "OnlyOne": true, "SRTHash": 752850861, "Translate": [0.0, 25.5, -24.0], "UnitConfigName": "DgnObj_Hrl_GoalSystemTop_01"}, {"!Parameters": {"DropTable": "Normal", "SharpWeaponJudgeType": 0}, "HashId": 852920326, "SRTHash": -1178587906, "Translate": [-8.0, 2.0, -12.0], "UnitConfigName": "DgnObj_hrl_Pillar1x1x4_01"}, {"!Parameters": {"DropTable": "Normal", "SharpWeaponJudgeType": 0}, "HashId": 875958368, "Rotate": 1.5707963705062866, "SRTHash": -609435702, "Translate": [-24.0, 0.0, 24.0], "UnitConfigName": "DgnObj_Hrl_Box4x4x6_03"}, {"!Parameters": {"DropTable": "Normal", "SharpWeaponJudgeType": 0}, "HashId": 893034708, "OnlyOne": true, "SRTHash": 1145155092, "Translate": [10.0, 0.0, -32.0], "UnitConfigName": "DgnObj_hrl_Box4x4x2_01"}, {"!Parameters": {"DropTable": "Normal", "SharpWeaponJudgeType": 0}, "HashId": 930297395, "SRTHash": 363979386, "Translate": [2.0, 6.0, -16.0], "UnitConfigName": "DgnObj_Hrl_Box4x4x2Top_01"}, {"!Parameters": {"DropTable": "Normal", "SharpWeaponJudgeType": 0}, "HashId": 931257565, "Rotate": -1.5707963705062866, "SRTHash": -1879426183, "Translate": [24.0, 0.0, -20.0], "UnitConfigName": "DgnObj_Hrl_Box4x4x6_03"}, {"!Parameters": {"DropTable": "Normal", "SharpWeaponJudgeType": 0}, "HashId": 952805809, "SRTHash": -1831658010, "Translate": [3.0, 6.0, 0.0], "UnitConfigName": "DgnObj_Hrl_CandlePoleB_01"}, {"!Parameters": {"DropTable": "Normal", "SharpWeaponJudgeType": 0}, "HashId": 986578251, "Rotate": 1.5707963705062866, "SRTHash": 171050473, "Translate": [4.0, 2.0, 0.0], "UnitConfigName": "DgnObj_Hrl_Box4x4x4_03"}, {"!Parameters": {"DropTable": "Normal", "SharpWeaponJudgeType": 0}, "HashId": 1002524159, "SRTHash": 1563697321, "Translate": [5.0, 4.0, -33.0], "UnitConfigName": "DgnObj_Hrl_Box2x2x4Top_01"}, {"HashId": 1009607981, "SRTHash": 592125259, "Translate": [-32.0, 12.0, -8.0], "UnitConfigName": "DgnObj_Hrl_BoxCover4x4_01"}, {"HashId": 1074650811, "SRTHash": -1317492167, "Translate": [32.0, 12.0, 24.0], "UnitConfigName": "DgnObj_Hrl_BoxCover4x4_01"}, {"!Parameters": {"DropTable": "Normal", "SharpWeaponJudgeType": 0}, "HashId": 1078140070, "Rotate": -1.5707963705062866, "SRTHash": 553475103, "Translate": [-6.0, 2.0, -20.0], "UnitConfigName": "DgnObj_Hrl_Box4x4x6_03"}, {"!Parameters": {"DropTable": "Normal", "SharpWeaponJudgeType": 0}, "HashId": 1090612751, "SRTHash": -1813654462, "Translate": [-3.0, 6.0, -8.0], "UnitConfigName": "DgnObj_Hrl_CandlePoleB_01"}, {"!Parameters": {"DropTable": "Normal", "SharpWeaponJudgeType": 0}, "HashId": 1142487241, "Rotate": -1.5707963705062866, "SRTHash": 686032083, "Translate": [24.0, 0.0, 24.0], "UnitConfigName": "DgnObj_Hrl_Box4x4x6_03"}, {"!Parameters": {"DropTable": "Normal", "SharpWeaponJudgeType": 0}, "HashId": 1189955293, "SRTHash": -2072997639, "Translate": [8.0, 0.0, -2.0], "UnitConfigName": "DgnObj_hrl_Box8x8x2_01"}, {"!Parameters": {"DropTable": "Normal", "SharpWeaponJudgeType": 0}, "HashId": 1197334170, "Rotate": 1.5707963705062866, "SRTHash": 1854419856, "Translate": [-28.0, 0.0, -18.0], "UnitConfigName": "DgnObj_Hrl_Box4x8x12_01"}, {"!Parameters": {"DropTable": "Normal", "SharpWeaponJudgeType": 0}, "HashId": 1209445366, "Rotate": -1.5707963705062866, "SRTHash": -835755782, "Translate": [24.0, 0.0, -28.0], "UnitConfigName": "DgnObj_Hrl_Box4x4x6_03"}, {"!Parameters": {"DropTable": "Normal", "SharpWeaponJudgeType": 0}, "HashId": 1222918424, "Rotate": -1.5707963705062866, "SRTHash": 1212307864, "Translate": [-4.0, 2.0, 0.0], "UnitConfigName": "DgnObj_Hrl_Box4x4x4_03"}, {"!Parameters": {"DropTable": "Normal", "SharpWeaponJudgeType": 0}, "HashId": 1256396258, "SRTHash": 2070874839, "Translate": [0.0, 0.0, 14.0], "UnitConfigName": "DgnObj_hrl_Box8x8x2_01"}, {"!Parameters": {"DropTable": "Normal", "SharpWeaponJudgeType": 0}, "HashId": 1275301252, "SRTHash": 492283945, "Translate": [2.0, 6.0, -32.0], "UnitConfigName": "DgnObj_Hrl_Box4x4x2Top_01"}, {"!Parameters": {"DropTable": "Normal", "SharpWeaponJudgeType": 0}, "HashId": 1359396156, "SRTHash": 1563697321, "Translate": [5.0, 4.0, -31.0], "UnitConfigName": "DgnObj_Hrl_Box2x2x4Top_01"}, {"!Parameters": {"DropTable": "Normal", "SharpWeaponJudgeType": 0}, "HashId": 1427348302, "SRTHash": 99045186, "Translate": [2.0, 0.0, -28.0], "UnitConfigName": "DgnObj_Hrl_Box4x4x6Under_01"}, {"!Parameters": {"DropTable": "Normal", "SharpWeaponJudgeType": 0}, "HashId": 1440838048, "SRTHash": -119235708, "Translate": [4.5, 8.0, -15.0], "UnitConfigName": "DgnObj_Hrl_TowerRoof2x2_A_01"}, {"HashId": 1458214382, "SRTHash": 883726394, "Translate": [32.0, 12.0, 16.0], "UnitConfigName": "DgnObj_Hrl_BoxCover4x4_01"}, {"!Parameters": {"DropTable": "Normal", "SharpWeaponJudgeType": 0}, "HashId": 1474700634, "Rotate": -1.5707963705062866, "SRTHash": 1573512804, "Translate": [24.0, 0.0, 8.0], "UnitConfigName": "DgnObj_Hrl_Box4x4x6_03"}, {"HashId": 1477540037, "Rotate": 3.1415927410125732, "SRTHash": 1054731263, "Translate": [0.0, 2.0, 13.0], "UnitConfigName": "DgnObj_Hrl_RoadEnd4x4_01"}, {"!Parameters": {"DropTable": "Normal", "SharpWeaponJudgeType": 0}, "HashId": 1495124081, "Rotate": -1.5707963705062866, "SRTHash": 1955050917, "Translate": [24.0, 0.0, 16.0], "UnitConfigName": "DgnObj_Hrl_Box4x4x6_03"}, {"!Parameters": {"DropTable": "Normal", "SharpWeaponJudgeType": 0}, "HashId": 1521091788, "SRTHash": 32702232, "Translate": [28.0, 12.0, -24.0], "UnitConfigName": "DgnObj_Hrl_TowerRoof4x4_A_01"}, {"!Parameters": {"DropTable": "Normal", "SharpWeaponJudgeType": 0}, "HashId": 1541961317, "Rotate": 1.5707963705062866, "SRTHash": -40573748, "Translate": [4.0, 2.0, -4.0], "UnitConfigName": "DgnObj_Hrl_Box4x4x4_03"}, {"!Parameters": {"DropTable": "Normal", "SharpWeaponJudgeType": 0}, "HashId": 1560866307, "SRTHash": -629883365, "Translate": [28.0, 6.0, 28.0], "UnitConfigName": "DgnObj_Hrl_Box4x4x6Top_01"}, {"HashId": 1610436631, "SRTHash": 282084175, "Translate": [0.0, 8.0, -16.5], "UnitConfigName": "DgnObj_Hrl_RoadEnd4x4_01"}, {"HashId": 1626253217, "SRTHash": -10591794, "Translate": [-10.0, 2.0, -32.0], "UnitConfigName": "DgnObj_Hrl_BoxCover4x4_01"}, {"!Parameters": {"DropTable": "Normal", "SharpWeaponJudgeType": 0}, "HashId": 1645943221, "Rotate": [0.0, 0.0, -3.1415927410125732], "SRTHash": 243239258, "Translate": [0.0, 26.5, -24.0], "UnitConfigName": "DgnObj_Hrl_GoalSystemCenter_01"}, {"!Parameters": {"DropTable": "Normal", "SharpWeaponJudgeType": 0}, "HashId": 1694204371, "Rotate": -1.5707963705062866, "SRTHash": 1816653485, "Translate": [24.0, 0.0, 28.0], "UnitConfigName": "DgnObj_Hrl_Box4x4x6_03"}, {"!Parameters": {"DropTable": "Normal", "SharpWeaponJudgeType": 0}, "HashId": 1712209863, "Rotate": -1.5707963705062866, "SRTHash": 1399614918, "Translate": [-4.0, 2.0, -12.0], "UnitConfigName": "DgnObj_Hrl_Box4x4x4_03"}, {"!Parameters": {"DropTable": "Normal", "SharpWeaponJudgeType": 0}, "HashId": 1728221043, "SRTHash": 154341273, "Translate": [-28.0, 6.0, 28.0], "UnitConfigName": "DgnObj_Hrl_Box4x4x6Top_01"}, {"!Parameters": {"DropTable": "Normal", "SharpWeaponJudgeType": 0}, "HashId": 1733053806, "SRTHash": -1695777778, "Translate": [-2.0, 6.0, -24.0], "UnitConfigName": "DgnObj_Hrl_Box4x4x2Top_01"}, {"!Parameters": {"DropTable": "Normal", "SharpWeaponJudgeType": 0}, "HashId": 1740547968, "SRTHash": -52982815, "Translate": [28.0, 12.0, -12.0], "UnitConfigName": "DgnObj_Hrl_TowerRoof4x4_A_01"}, {"!Parameters": {"DropTable": "Normal", "SharpWeaponJudgeType": 0}, "HashId": 1745303554, "SRTHash": -58150470, "Translate": [-2.0, 0.0, -20.0], "UnitConfigName": "DgnObj_Hrl_Box4x4x6Under_01"}, {"!Parameters": {"DropTable": "Normal", "SharpWeaponJudgeType": 0}, "HashId": 1778412792, "OnlyOne": true, "SRTHash": 1468833002, "Translate": [0.0, 2.0, 8.0], "UnitConfigName": "DgnObj_hrl_Stair8x4x4_01"}, {"HashId": 1826682014, "SRTHash": 348219920, "Translate": [32.0, 12.0, -8.0], "UnitConfigName": "DgnObj_Hrl_BoxCover4x4_01"}, {"!Parameters": {"DropTable": "Normal", "SharpWeaponJudgeType": 0}, "HashId": 1846889098, "OnlyOne": true, "SRTHash": 849284493, "Translate": [0.0, 7.5, 26.0], "UnitConfigName": "DgnObj_Hrl_CeilingPillarA_01"}, {"!Parameters": {"DropTable": "Normal", "SharpWeaponJudgeType": 0}, "HashId": 1894347922, "Rotate": 1.5707963705062866, "SRTHash": -1642376030, "Translate": [-28.0, 0.0, 14.0], "UnitConfigName": "DgnObj_Hrl_Box4x8x12_01"}, {"HashId": 1910883366, "SRTHash": 679503879, "Translate": [-32.0, 12.0, 24.0], "UnitConfigName": "DgnObj_Hrl_BoxCover4x4_01"}, {"!Parameters": {"DropTable": "Normal", "SharpWeaponJudgeType": 0}, "HashId": 1930459698, "OnlyOne": true, "SRTHash": 1847911410, "Translate": [0.0, 24.5, 26.0], "UnitConfigName": "DgnObj_Hrl_CeilingPillarA_02"}, {"!Parameters": {"DropTable": "Normal", "SharpWeaponJudgeType": 0}, "HashId": 1963067578, "SRTHash": 1671543842, "Translate": [0.0, 0.0, 2.0], "UnitConfigName": "DgnObj_hrl_Box8x8x2_01"}, {"!Parameters": {"DropTable": "Normal", "SharpWeaponJudgeType": 0}, "HashId": 1996840000, "SRTHash": -439002403, "Translate": [8.0, 0.0, 6.0], "UnitConfigName": "DgnObj_hrl_Box8x8x2_01"}, {"!Parameters": {"DropTable": "Normal", "SharpWeaponJudgeType": 0}, "HashId": 2046734699, "Rotate": 1.5707963705062866, "SRTHash": -1511370984, "Translate": [-28.0, 0.0, 22.0], "UnitConfigName": "DgnObj_Hrl_Box4x8x12_01"}, {"!Parameters": {"DropTable": "Normal", "SharpWeaponJudgeType": 0}, "HashId": 2051636694, "Rotate": 1.5707963705062866, "SRTHash": 1229979065, "Translate": [-24.0, 0.0, -20.0], "UnitConfigName": "DgnObj_Hrl_Box4x4x6_03"}, {"!Parameters": {"DropTable": "Normal", "SharpWeaponJudgeType": 0}, "HashId": 2059114296, "Rotate": -1.5707963705062866, "SRTHash": -1487227758, "Translate": [24.0, 0.0, -12.0], "UnitConfigName": "DgnObj_Hrl_Box4x4x6_03"}, {"!Parameters": {"DropTable": "Normal", "SharpWeaponJudgeType": 0}, "HashId": 2064322431, "Rotate": 1.5707963705062866, "SRTHash": -279171837, "Translate": [-28.0, 0.0, -10.0], "UnitConfigName": "DgnObj_Hrl_Box4x8x12_01"}, {"!Parameters": {"DropTable": "Normal", "SharpWeaponJudgeType": 0}, "HashId": 2102902762, "Rotate": 1.5707963705062866, "SRTHash": -1698052870, "Translate": [-24.0, 0.0, -16.0], "UnitConfigName": "DgnObj_Hrl_Box4x4x6_03"}, {"HashId": 2112591641, "SRTHash": 865331230, "Translate": [-6.0, 2.0, -32.0], "UnitConfigName": "DgnObj_Hrl_BoxCover4x4_01"}, {"!Parameters": {"DropTable": "Normal", "SharpWeaponJudgeType": 0}, "HashId": 2115148217, "Rotate": 1.5707963705062866, "SRTHash": -700838495, "Translate": [28.0, 0.0, 22.0], "UnitConfigName": "DgnObj_Hrl_Box4x8x12_01"}, {"!Parameters": {"DropTable": "Normal", "SharpWeaponJudgeType": 0}, "HashId": 2132683021, "SRTHash": -831027416, "Translate": [8.0, 2.0, 1.0], "UnitConfigName": "DgnObj_hrl_Pillar1x1x4_01"}, {"!Parameters": {"DropTable": "Normal", "SharpWeaponJudgeType": 0}, "HashId": 2176828999, "Rotate": 1.5707963705062866, "SRTHash": 427873451, "Translate": [-24.0, 0.0, 12.0], "UnitConfigName": "DgnObj_Hrl_Box4x4x6_03"}, {"!Parameters": {"DropTable": "Normal", "SharpWeaponJudgeType": 0}, "HashId": 2209911485, "SRTHash": 1464510842, "Translate": [-3.0, 6.0, 0.0], "UnitConfigName": "DgnObj_Hrl_CandlePoleB_01"}, {"!Parameters": {"DropTable": "Normal", "SharpWeaponJudgeType": 0}, "HashId": 2225492097, "Rotate": 1.5707963705062866, "SRTHash": 1797472505, "Translate": [-24.0, 0.0, 0.0], "UnitConfigName": "DgnObj_Hrl_Box4x4x6_03"}, {"!Parameters": {"DropTable": "Normal", "SharpWeaponJudgeType": 0}, "HashId": 2271174177, "SRTHash": 710835978, "Translate": [-2.0, 6.0, -32.0], "UnitConfigName": "DgnObj_Hrl_Box4x4x2Top_01"}, {"!Parameters": {"DropTable": "Normal", "SharpWeaponJudgeType": 0}, "HashId": 2321399210, "SRTHash": 326360435, "Translate": [3.0, 6.0, -8.0], "UnitConfigName": "DgnObj_Hrl_CandlePoleB_01"}, {"!Parameters": {"DropTable": "Normal", "SharpWeaponJudgeType": 0}, "HashId": 2334117635, "Rotate": 1.5707963705062866, "SRTHash": -1307986436, "Translate": [6.0, 2.0, -20.0], "UnitConfigName": "DgnObj_Hrl_Box4x4x6_03"}, {"!Parameters": {"DropTable": "Normal", "SharpWeaponJudgeType": 0}, "HashId": 2337344798, "SRTHash": 272847263, "Translate": [-4.0, 8.0, -32.02000045776367], "UnitConfigName": "DgnObj_Hrl_Box4x4Wainscot_01"}, {"!Parameters": {"DropTable": "Normal", "SharpWeaponJudgeType": 0}, "HashId": 2348879167, "Rotate": 1.5707963705062866, "SRTHash": 1766366510, "Translate": [6.0, 2.0, -16.0], "UnitConfigName": "DgnObj_Hrl_Box4x4x6_03"}, {"!Parameters": {"DropTable": "Normal", "SharpWeaponJudgeType": 0}, "HashId": 2377225592, "SRTHash": 1486182333, "Translate": [-8.0, 0.0, -2.0], "UnitConfigName": "DgnObj_hrl_Box8x8x2_01"}, {"!Parameters": {"DropTable": "Normal", "SharpWeaponJudgeType": 0}, "HashId": 2403609452, "Rotate": -1.5707963705062866, "SRTHash": 374457291, "Translate": [24.0, 0.0, 20.0], "UnitConfigName": "DgnObj_Hrl_Box4x4x6_03"}, {"!Parameters": {"DropTable": "Normal", "SharpWeaponJudgeType": 0}, "HashId": 2427758016, "Rotate": 1.5707963705062866, "SRTHash": -323596336, "Translate": [-24.0, 0.0, -4.0], "UnitConfigName": "DgnObj_Hrl_Box4x4x6_03"}, {"!Parameters": {"DropTable": "Normal", "SharpWeaponJudgeType": 0}, "HashId": 2448873321, "Rotate": 1.5707963705062866, "SRTHash": -1360528617, "Translate": [28.0, 0.0, -26.0], "UnitConfigName": "DgnObj_Hrl_Box4x8x12_01"}, {"!Parameters": {"DropTable": "Normal", "SharpWeaponJudgeType": 0}, "HashId": 2453740500, "SRTHash": -2043289657, "Translate": [28.0, 12.0, 12.0], "UnitConfigName": "DgnObj_Hrl_TowerRoof4x4_A_01"}, {"HashId": 2471340896, "OnlyOne": true, "SRTHash": -267271329, "Translate": [0.0, 2.0, 17.0], "UnitConfigName": "DgnObj_Hrl_Road4x4_01"}, {"HashId": 2493612978, "Rotate": 3.1415927410125732, "SRTHash": -2085023885, "Translate": [0.0, 8.0, -20.5], "UnitConfigName": "DgnObj_Hrl_RoadEnd4x4_01"}, {"HashId": 2522103206, "SRTHash": 1641157199, "Translate": [28.0, 0.0, 28.0], "UnitConfigName": "DgnObj_Hrl_Box4x4x6Center_01"}, {"!Parameters": {"DropTable": "Normal", "SharpWeaponJudgeType": 0}, "HashId": 2589617817, "Rotate": -3.1415927410125732, "SRTHash": -1072520381, "Translate": [-3.0, 2.0, 31.209999084472656], "UnitConfigName": "DgnObj_Hrl_Box2x2Wainscot_01"}, {"!Parameters": {"DropTable": "Normal", "SharpWeaponJudgeType": 0}, "HashId": 2629498623, "Rotate": 1.5707963705062866, "SRTHash": 373372182, "Translate": [28.0, 0.0, 6.0], "UnitConfigName": "DgnObj_Hrl_Box4x8x12_01"}, {"HashId": 2645968459, "SRTHash": 883726394, "Translate": [32.0, 12.0, 8.0], "UnitConfigName": "DgnObj_Hrl_BoxCover4x4_01"}, {"!Parameters": {"DropTable": "Normal", "SharpWeaponJudgeType": 0}, "HashId": 2655996139, "SRTHash": -458112094, "Translate": [-2.0, 0.0, -28.0], "UnitConfigName": "DgnObj_Hrl_Box4x4x6Under_01"}, {"!Parameters": {"DropTable": "Normal", "SharpWeaponJudgeType": 0}, "HashId": 2707210077, "SRTHash": 1265005366, "Translate": [0.0, 0.0, 6.0], "UnitConfigName": "DgnObj_hrl_Box8x8x2_01"}, {"!Parameters": {"DropTable": "Normal", "SharpWeaponJudgeType": 0}, "HashId": 2740710311, "SRTHash": 1608562750, "Translate": [-2.0, 0.0, -16.5], "UnitConfigName": "DgnObj_Hrl_Box4x4x6Under_01"}, {"!Parameters": {"DropTable": "Normal", "SharpWeaponJudgeType": 0}, "HashId": 2745762121, "SRTHash": -905228792, "Translate": [2.0, 6.0, -28.0], "UnitConfigName": "DgnObj_Hrl_Box4x4x2Top_01"}, {"!Parameters": {"DropTable": "Normal", "SharpWeaponJudgeType": 0}, "HashId": 2773063983, "SRTHash": 677356061, "Translate": [0.0, 16.5, 26.0], "UnitConfigName": "DgnObj_Hrl_CeilingPillarA_03"}, {"HashId": 2814125883, "SRTHash": 812492697, "Translate": [32.0, 12.0, -24.0], "UnitConfigName": "DgnObj_Hrl_BoxCover4x4_01"}, {"HashId": 2840054288, "SRTHash": -903868942, "Translate": [0.0, 2.0, 21.0], "UnitConfigName": "DgnObj_Hrl_RoadEnd4x4_01"}, {"!Parameters": {"DropTable": "Normal", "SharpWeaponJudgeType": 0}, "HashId": 2886770379, "Rotate": -1.5707963705062866, "SRTHash": -1711241763, "Translate": [-6.0, 2.0, -24.0], "UnitConfigName": "DgnObj_Hrl_Box4x4x6_03"}, {"HashId": 2891865302, "SRTHash": -1883499043, "Translate": [-28.0, 0.0, 28.0], "UnitConfigName": "DgnObj_Hrl_Box4x4x6Center_01"}, {"!Parameters": {"DropTable": "Normal", "SharpWeaponJudgeType": 0}, "HashId": 2900522021, "Rotate": 1.5707963705062866, "SRTHash": -1070585869, "Translate": [-24.0, 0.0, -12.0], "UnitConfigName": "DgnObj_Hrl_Box4x4x6_03"}, {"!Parameters": {"DropTable": "Normal", "SharpWeaponJudgeType": 0}, "HashId": 2907892834, "OnlyOne": true, "SRTHash": -712969426, "Translate": [0.0, 6.0, -12.0], "UnitConfigName": "DgnObj_hrl_Stair4x4x2_01"}, {"!Parameters": {"DropTable": "Normal", "SharpWeaponJudgeType": 0}, "HashId": 2946978422, "Rotate": 1.5707963705062866, "SRTHash": -238249242, "Translate": [-24.0, 0.0, 28.0], "UnitConfigName": "DgnObj_Hrl_Box4x4x6_03"}, {"!Parameters": {"DropTable": "Normal", "SharpWeaponJudgeType": 0}, "HashId": 2958548186, "Rotate": -1.5707963705062866, "SRTHash": 911555751, "Translate": [24.0, 0.0, -8.0], "UnitConfigName": "DgnObj_Hrl_Box4x4x6_03"}, {"!Parameters": {"DropTable": "Normal", "SharpWeaponJudgeType": 0}, "HashId": 2970988147, "SRTHash": 114262653, "Translate": [8.0, 0.0, -18.0], "UnitConfigName": "DgnObj_hrl_Box8x8x2_01"}, {"!Parameters": {"DropTable": "Normal", "SharpWeaponJudgeType": 0}, "HashId": 2984723613, "SRTHash": 473593924, "Translate": [8.0, 0.0, -10.0], "UnitConfigName": "DgnObj_hrl_Box8x8x2_01"}, {"!Parameters": {"DropTable": "Normal", "SharpWeaponJudgeType": 0}, "HashId": 2996986574, "Rotate": 1.5707963705062866, "SRTHash": 276417293, "Translate": [-24.0, 0.0, 20.0], "UnitConfigName": "DgnObj_Hrl_Box4x4x6_03"}, {"!Parameters": {"DropTable": "Normal", "SharpWeaponJudgeType": 0}, "HashId": 3024288424, "SRTHash": 631888162, "Translate": [-8.0, 2.0, 1.0], "UnitConfigName": "DgnObj_hrl_Pillar1x1x4_01"}, {"!Parameters": {"DropTable": "Normal", "SharpWeaponJudgeType": 0}, "HashId": 3041806876, "SRTHash": -776058098, "Translate": [0.0, 0.0, 22.0], "UnitConfigName": "DgnObj_hrl_Box8x8x2_01"}, {"!Parameters": {"DropTable": "Normal", "SharpWeaponJudgeType": 0}, "HashId": 3054201935, "Rotate": -1.5707963705062866, "SRTHash": 505435108, "Translate": [-6.0, 2.0, -16.0], "UnitConfigName": "DgnObj_Hrl_Box4x4x6_03"}, {"!Parameters": {"DropTable": "Normal", "SharpWeaponJudgeType": 0}, "HashId": 3065463996, "SRTHash": 259114396, "Translate": [-8.0, 2.0, -32.20000076293945], "UnitConfigName": "DgnObj_Hrl_Box4x4Wainscot_01"}, {"!Parameters": {"DropTable": "Normal", "SharpWeaponJudgeType": 0}, "HashId": 3092031895, "Rotate": [0.0, 0.0, 3.1415927410125732], "SRTHash": -189432538, "Translate": [0.0, 24.5, 26.0], "UnitConfigName": "DgnObj_Hrl_CeilingPillarA_03"}, {"HashId": 3132692355, "SRTHash": -2083315373, "Translate": [-32.0, 12.0, 8.0], "UnitConfigName": "DgnObj_Hrl_BoxCover4x4_01"}, {"!Parameters": {"DropTable": "Normal", "SharpWeaponJudgeType": 0}, "HashId": 3149244215, "Rotate": 1.5707963705062866, "SRTHash": -703190493, "Translate": [28.0, 0.0, 14.0], "UnitConfigName": "DgnObj_Hrl_Box4x8x12_01"}, {"!Parameters": {"DropTable": "Normal", "SharpWeaponJudgeType": 0}, "HashId": 3159986149, "Rotate": -1.5707963705062866, "SRTHash": -1582703062, "Translate": [24.0, 0.0, 4.0], "UnitConfigName": "DgnObj_Hrl_Box4x4x6_03"}, {"!Parameters": {"DropTable": "Normal", "SharpWeaponJudgeType": 0}, "HashId": 3193887519, "SRTHash": 1150394864, "Translate": [2.0, 0.0, -16.0], "UnitConfigName": "DgnObj_Hrl_Box4x4x6Under_01"}, {"!Parameters": {"DropTable": "Normal", "SharpWeaponJudgeType": 0}, "HashId": 3198956017, "Rotate": -1.5707963705062866, "SRTHash": -918142347, "Translate": [24.0, 0.0, 0.0], "UnitConfigName": "DgnObj_Hrl_Box4x4x6_03"}, {"!Parameters": {"DropTable": "Normal", "SharpWeaponJudgeType": 0}, "HashId": 3229168755, "Rotate": -1.5707963705062866, "SRTHash": 38399784, "Translate": [24.0, 0.0, -4.0], "UnitConfigName": "DgnObj_Hrl_Box4x4x6_03"}, {"!Parameters": {"DropTable": "Normal", "SharpWeaponJudgeType": 0}, "HashId": 3251219508, "Rotate": -1.5707963705062866, "SRTHash": -189852144, "Translate": [24.0, 0.0, -16.0], "UnitConfigName": "DgnObj_Hrl_Box4x4x6_03"}, {"!Parameters": {"DropTable": "Normal", "SharpWeaponJudgeType": 0}, "HashId": 3263990375, "SRTHash": 1608234537, "Translate": [-28.0, 12.0, 12.0], "UnitConfigName": "DgnObj_Hrl_TowerRoof4x4_A_01"}, {"!Parameters": {"DropTable": "Normal", "SharpWeaponJudgeType": 0}, "HashId": 3331959829, "Rotate": -1.5707963705062866, "SRTHash": -1165560680, "Translate": [8.0, 8.0, -32.0], "UnitConfigName": "DgnObj_Hrl_Box4x4Wainscot_01"}, {"!Parameters": {"DropTable": "Normal", "SharpWeaponJudgeType": 0}, "HashId": 3430377292, "Rotate": -1.5707963705062866, "SRTHash": 502086275, "Translate": [24.0, 0.0, 12.0], "UnitConfigName": "DgnObj_Hrl_Box4x4x6_03"}, {"!Parameters": {"DropTable": "Normal", "SharpWeaponJudgeType": 0}, "HashId": 3463459766, "SRTHash": -1606702962, "Translate": [0.0, 0.0, 0.0], "UnitConfigName": "DgnObj_hrl_Box4x4x6_01"}, {"!Parameters": {"DropTable": "Normal", "SharpWeaponJudgeType": 0}, "HashId": 3513931764, "SRTHash": 550470387, "Translate": [10.0, 2.0, 8.0], "UnitConfigName": "DgnObj_Hrl_TowerRoof4x4_A_01"}, {"!Parameters": {"DropTable": "Normal", "SharpWeaponJudgeType": 0}, "HashId": 3548899808, "Rotate": 1.5707963705062866, "SRTHash": -291682245, "Translate": [6.0, 2.0, -28.0], "UnitConfigName": "DgnObj_Hrl_Box4x4x6_03"}, {"!Parameters": {"DropTable": "Normal", "SharpWeaponJudgeType": 0}, "HashId": 3566808028, "SRTHash": -1544497140, "Translate": [2.0, 0.0, -24.0], "UnitConfigName": "DgnObj_Hrl_Box4x4x6Under_01"}, {"!Parameters": {"DropTable": "Normal", "SharpWeaponJudgeType": 0}, "HashId": 3600711462, "Rotate": 1.5707963705062866, "SRTHash": -1004182189, "Translate": [-28.0, 0.0, 6.0], "UnitConfigName": "DgnObj_Hrl_Box4x8x12_01"}, {"!Parameters": {"DropTable": "Normal", "SharpWeaponJudgeType": 0}, "HashId": 3616722834, "Rotate": -3.1415927410125732, "SRTHash": -1030384519, "Translate": [2.0, 2.0, 32.0], "UnitConfigName": "DgnObj_Hrl_Box4x4Wainscot_01"}, {"!Parameters": {"DropTable": "Normal", "SharpWeaponJudgeType": 0}, "HashId": 3630535181, "SRTHash": 2016211333, "Translate": [-28.0, 12.0, 24.0], "UnitConfigName": "DgnObj_Hrl_TowerRoof4x4_A_01"}, {"HashId": 3647546041, "Rotate": 3.1415927410125732, "SRTHash": -752963815, "Translate": [0.0, 6.0, -7.5], "UnitConfigName": "DgnObj_Hrl_RoadEnd4x4_01"}, {"!Parameters": {"DropTable": "Normal", "SharpWeaponJudgeType": 0}, "HashId": 3676353630, "Rotate": 1.5707963705062866, "SRTHash": -129054375, "Translate": [4.0, 2.0, -8.0], "UnitConfigName": "DgnObj_Hrl_Box4x4x4_03"}, {"!Parameters": {"DropTable": "Normal", "SharpWeaponJudgeType": 0}, "HashId": 3684474029, "SRTHash": -2107611699, "Translate": [10.0, 2.0, -28.0], "UnitConfigName": "DgnObj_Hrl_TowerRoof2x2_A_01"}, {"!Parameters": {"DropTable": "Normal", "SharpWeaponJudgeType": 0}, "HashId": 3695081058, "SRTHash": -524288833, "Translate": [8.0, 0.0, -26.0], "UnitConfigName": "DgnObj_hrl_Box8x8x2_01"}, {"!Parameters": {"DropTable": "Normal", "SharpWeaponJudgeType": 0}, "HashId": 3704396940, "SRTHash": -549615788, "Translate": [2.0, 6.0, -20.0], "UnitConfigName": "DgnObj_Hrl_Box4x4x2Top_01"}, {"!Parameters": {"DropTable": "Normal", "SharpWeaponJudgeType": 0}, "HashId": 3715892427, "Rotate": -1.5707963705062866, "SRTHash": -161366045, "Translate": [-4.0, 2.0, -4.0], "UnitConfigName": "DgnObj_Hrl_Box4x4x4_03"}, {"HashId": 3738628573, "OnlyOne": true, "Rotate": -3.1415927410125732, "SRTHash": 955776311, "Translate": [0.0, 2.0, 21.0], "UnitConfigName": "DungeonResetPosTag"}, {"!Parameters": {"DropTable": "Normal", "SharpWeaponJudgeType": 0}, "HashId": 3768208745, "Rotate": -1.5707963705062866, "SRTHash": 396447001, "Translate": [-4.0, 2.0, -8.0], "UnitConfigName": "DgnObj_Hrl_Box4x4x4_03"}, {"!Parameters": {"DropTable": "Normal", "SharpWeaponJudgeType": 0}, "HashId": 3777680686, "SRTHash": 886790116, "Translate": [-28.0, 12.0, -12.0], "UnitConfigName": "DgnObj_Hrl_TowerRoof4x4_A_01"}, {"!Parameters": {"DropTable": "Normal", "SharpWeaponJudgeType": 0}, "HashId": 3789045696, "Rotate": 1.5707963705062866, "SRTHash": 1546403059, "Translate": [-28.0, 0.0, -26.0], "UnitConfigName": "DgnObj_Hrl_Box4x8x12_01"}, {"!Parameters": {"DropTable": "Normal", "SharpWeaponJudgeType": 0}, "HashId": 3798987645, "SRTHash": -776058098, "Translate": [0.0, 0.0, 30.0], "UnitConfigName": "DgnObj_hrl_Box8x8x2_01"}, {"!Parameters": {"DropTable": "Normal", "SharpWeaponJudgeType": 0}, "HashId": 3834604315, "SRTHash": -1874250219, "Translate": [0.0, 22.5, -24.0], "UnitConfigName": "DgnObj_Hrl_GoalSystemCenter_01"}, {"!Parameters": {"DropTable": "Normal", "SharpWeaponJudgeType": 0}, "HashId": 3862173458, "SRTHash": -981108906, "Translate": [2.0, 6.0, -24.0], "UnitConfigName": "DgnObj_Hrl_Box4x4x2Top_01"}, {"!Parameters": {"DropTable": "Normal", "SharpWeaponJudgeType": 0}, "HashId": 3883296187, "SRTHash": -277451458, "Translate": [0.0, 0.5, -4.0], "UnitConfigName": "DgnObj_hrl_Box4x4x6_01"}, {"!Parameters": {"DropTable": "Normal", "SharpWeaponJudgeType": 0}, "HashId": 3918366864, "Rotate": -1.5707963705062866, "SRTHash": -153302569, "Translate": [-6.0, 2.0, -28.0], "UnitConfigName": "DgnObj_Hrl_Box4x4x6_03"}, {"HashId": 3933505072, "SRTHash": 1439352486, "Translate": [-32.0, 12.0, -24.0], "UnitConfigName": "DgnObj_Hrl_BoxCover4x4_01"}, {"!Parameters": {"DropTable": "Normal", "SharpWeaponJudgeType": 0}, "HashId": 3969130070, "SRTHash": -280913101, "Translate": [-8.0, 0.0, 6.0], "UnitConfigName": "DgnObj_hrl_Box8x8x2_01"}, {"!Parameters": {"DropTable": "Normal", "SharpWeaponJudgeType": 0}, "HashId": 3999375426, "SRTHash": -1978009281, "Translate": [-8.0, 0.0, -18.0], "UnitConfigName": "DgnObj_hrl_Box8x8x2_01"}, {"!Parameters": {"DropTable": "Normal", "SharpWeaponJudgeType": 0}, "HashId": 4002630316, "SRTHash": 1776452760, "Translate": [2.0, 0.0, -20.0], "UnitConfigName": "DgnObj_Hrl_Box4x4x6Under_01"}, {"HashId": 4036861530, "SRTHash": 1397672956, "Translate": [-32.0, 12.0, 16.0], "UnitConfigName": "DgnObj_Hrl_BoxCover4x4_01"}, {"!Parameters": {"DropTable": "Normal", "SharpWeaponJudgeType": 0}, "HashId": 4052823790, "SRTHash": -2129741074, "Translate": [28.0, 12.0, 0.0], "UnitConfigName": "DgnObj_Hrl_TowerRoof4x4_A_01"}, {"HashId": 4151424648, "SRTHash": 156869482, "Translate": [-32.0, 12.0, -16.0], "UnitConfigName": "DgnObj_Hrl_BoxCover4x4_01"}, {"!Parameters": {"DropTable": "Normal", "SharpWeaponJudgeType": 0}, "HashId": 4186594211, "SRTHash": 977332335, "Translate": [8.0, 2.0, -12.0], "UnitConfigName": "DgnObj_hrl_Pillar1x1x4_01"}, {"!Parameters": {"DropTable": "Normal", "SharpWeaponJudgeType": 0}, "HashId": 4230997398, "SRTHash": -661276989, "Translate": [-2.0, 6.0, -16.0], "UnitConfigName": "DgnObj_Hrl_Box4x4x2Top_01"}, {"!Parameters": {"DropTable": "Normal", "SharpWeaponJudgeType": 0}, "HashId": 4242345848, "SRTHash": -201154337, "Translate": [-28.0, 12.0, -24.0], "UnitConfigName": "DgnObj_Hrl_TowerRoof4x4_A_01"}, {"!Parameters": {"DropTable": "Normal", "SharpWeaponJudgeType": 0}, "HashId": 4255088081, "SRTHash": -746125922, "Translate": [0.0, 0.0, -8.0], "UnitConfigName": "DgnObj_hrl_Box4x4x6_01"}, {"!Parameters": {"DropTable": "Normal", "SharpWeaponJudgeType": 0}, "HashId": 4268127089, "SRTHash": -398505156, "Translate": [9.0, 2.0, -30.979999542236328], "UnitConfigName": "DgnObj_Hrl_Box2x2Wainscot_02"}], "Rails": []}