{"Objs": [{"!Parameters": {"DropTable": "Normal", "SharpWeaponJudgeType": 0}, "HashId": 5693124, "SRTHash": -661276989, "Translate": [-2.0, 6.0, -16.0], "UnitConfigName": "DgnObj_Hrl_Box4x4x2Top_01"}, {"!Parameters": {"DropTable": "Normal", "SharpWeaponJudgeType": 0}, "HashId": 10761258, "SRTHash": -201154337, "Translate": [-28.0, 12.0, -24.0], "UnitConfigName": "DgnObj_Hrl_TowerRoof4x4_A_01"}, {"!Parameters": {"DropTable": "Normal", "SharpWeaponJudgeType": 0}, "HashId": 16733033, "SRTHash": -2043289657, "Translate": [28.0, 12.0, 12.0], "UnitConfigName": "DgnObj_Hrl_TowerRoof4x4_A_01"}, {"HashId": 32760797, "OnlyOne": true, "SRTHash": -267271329, "Translate": [0.0, 2.0, 17.0], "UnitConfigName": "DgnObj_Hrl_Road4x4_01"}, {"!Parameters": {"DropTable": "Normal", "SharpWeaponJudgeType": 0}, "HashId": 34270589, "Rotate": 1.5707963705062866, "SRTHash": -323596336, "Translate": [-24.0, 0.0, -4.0], "UnitConfigName": "DgnObj_Hrl_Box4x4x6_03"}, {"HashId": 82474267, "SRTHash": 1641157199, "Translate": [28.0, 0.0, 28.0], "UnitConfigName": "DgnObj_Hrl_Box4x4x6Center_01"}, {"HashId": 102746895, "Rotate": 3.1415927410125732, "SRTHash": -2085023885, "Translate": [0.0, 8.0, -20.5], "UnitConfigName": "DgnObj_Hrl_RoadEnd4x4_01"}, {"!Parameters": {"DropTable": "Normal", "SharpWeaponJudgeType": 0}, "HashId": 149169700, "Rotate": -3.1415927410125732, "SRTHash": -1072520381, "Translate": [-3.0, 2.0, 31.209999084472656], "UnitConfigName": "DgnObj_Hrl_Box2x2Wainscot_01"}, {"!Parameters": {"DropTable": "Normal", "SharpWeaponJudgeType": 0}, "HashId": 217120854, "SRTHash": -458112094, "Translate": [-2.0, 0.0, -28.0], "UnitConfigName": "DgnObj_Hrl_Box4x4x6Under_01"}, {"!Parameters": {"DropTable": "Normal", "SharpWeaponJudgeType": 0}, "HashId": 235191874, "Rotate": 1.5707963705062866, "SRTHash": 373372182, "Translate": [28.0, 0.0, 6.0], "UnitConfigName": "DgnObj_Hrl_Box4x8x12_01"}, {"HashId": 252186358, "SRTHash": 883726394, "Translate": [32.0, 12.0, 8.0], "UnitConfigName": "DgnObj_Hrl_BoxCover4x4_01"}, {"!Parameters": {"DropTable": "Normal", "SharpWeaponJudgeType": 0}, "HashId": 285661696, "SRTHash": 1464510842, "Translate": [-3.0, 6.0, 0.0], "UnitConfigName": "DgnObj_Hrl_CandlePoleB_01"}, {"!Parameters": {"DropTable": "Normal", "SharpWeaponJudgeType": 0}, "HashId": 318869242, "Rotate": 1.5707963705062866, "SRTHash": 427873451, "Translate": [-24.0, 0.0, 12.0], "UnitConfigName": "DgnObj_Hrl_Box4x4x6_03"}, {"!Parameters": {"DropTable": "Normal", "SharpWeaponJudgeType": 0}, "HashId": 367072924, "SRTHash": 710835978, "Translate": [-2.0, 6.0, -32.0], "UnitConfigName": "DgnObj_Hrl_Box4x4x2Top_01"}, {"!Parameters": {"DropTable": "Normal", "SharpWeaponJudgeType": 0}, "HashId": 370677820, "Rotate": 1.5707963705062866, "SRTHash": 1797472505, "Translate": [-24.0, 0.0, 0.0], "UnitConfigName": "DgnObj_Hrl_Box4x4x6_03"}, {"!Parameters": {"DropTable": "Normal", "SharpWeaponJudgeType": 0}, "HashId": 417592599, "SRTHash": 326360435, "Translate": [3.0, 6.0, -8.0], "UnitConfigName": "DgnObj_Hrl_CandlePoleB_01"}, {"!Parameters": {"DropTable": "Normal", "SharpWeaponJudgeType": 0}, "HashId": 435111331, "SRTHash": 272847263, "Translate": [-4.0, 8.0, -32.02000045776367], "UnitConfigName": "DgnObj_Hrl_Box4x4Wainscot_01"}, {"!Parameters": {"DropTable": "Normal", "SharpWeaponJudgeType": 0}, "HashId": 441265216, "SRTHash": -981108906, "Translate": [2.0, 6.0, -24.0], "UnitConfigName": "DgnObj_Hrl_Box4x4x2Top_01"}, {"!Parameters": {"DropTable": "Normal", "SharpWeaponJudgeType": 0}, "HashId": 492039804, "SRTHash": 886790116, "Translate": [-28.0, 12.0, -12.0], "UnitConfigName": "DgnObj_Hrl_TowerRoof4x4_A_01"}, {"!Parameters": {"DropTable": "Normal", "SharpWeaponJudgeType": 0}, "HashId": 497091730, "Rotate": 1.5707963705062866, "SRTHash": 1546403059, "Translate": [-28.0, 0.0, -26.0], "UnitConfigName": "DgnObj_Hrl_Box4x8x12_01"}, {"!Parameters": {"DropTable": "Normal", "SharpWeaponJudgeType": 0}, "HashId": 502948817, "Rotate": -1.5707963705062866, "SRTHash": 374457291, "Translate": [24.0, 0.0, 20.0], "UnitConfigName": "DgnObj_Hrl_Box4x4x6_03"}, {"!Parameters": {"DropTable": "Normal", "SharpWeaponJudgeType": 0}, "HashId": 521133509, "SRTHash": 1486182333, "Translate": [-8.0, 0.0, -2.0], "UnitConfigName": "DgnObj_hrl_Box8x8x2_01"}, {"!Parameters": {"DropTable": "Normal", "SharpWeaponJudgeType": 0}, "HashId": 538716787, "Rotate": 1.5707963705062866, "SRTHash": 276417293, "Translate": [-24.0, 0.0, 20.0], "UnitConfigName": "DgnObj_Hrl_Box4x4x6_03"}, {"!Parameters": {"DropTable": "Normal", "SharpWeaponJudgeType": 0}, "HashId": 541543728, "SRTHash": -524288833, "Translate": [8.0, 0.0, -26.0], "UnitConfigName": "DgnObj_hrl_Box8x8x2_01"}, {"!Parameters": {"DropTable": "Normal", "SharpWeaponJudgeType": 0}, "HashId": 548775902, "SRTHash": -549615788, "Translate": [2.0, 6.0, -20.0], "UnitConfigName": "DgnObj_Hrl_Box4x4x2Top_01"}, {"!Parameters": {"DropTable": "Normal", "SharpWeaponJudgeType": 0}, "HashId": 585733223, "Rotate": -1.5707963705062866, "SRTHash": 911555751, "Translate": [24.0, 0.0, -8.0], "UnitConfigName": "DgnObj_Hrl_Box4x4x6_03"}, {"!Parameters": {"DropTable": "Normal", "SharpWeaponJudgeType": 0}, "HashId": 604572673, "SRTHash": 259114396, "Translate": [-8.0, 2.0, -32.20000076293945], "UnitConfigName": "DgnObj_Hrl_Box4x4Wainscot_01"}, {"!Parameters": {"DropTable": "Normal", "SharpWeaponJudgeType": 0}, "HashId": 654094869, "SRTHash": 631888162, "Translate": [-8.0, 2.0, 1.0], "UnitConfigName": "DgnObj_hrl_Pillar1x1x4_01"}, {"!Parameters": {"DropTable": "Normal", "SharpWeaponJudgeType": 0}, "HashId": 660180748, "Rotate": 1.5707963705062866, "SRTHash": -129054375, "Translate": [4.0, 2.0, -8.0], "UnitConfigName": "DgnObj_Hrl_Box4x4x4_03"}, {"!Parameters": {"DropTable": "Normal", "SharpWeaponJudgeType": 0}, "HashId": 670040737, "SRTHash": -776058098, "Translate": [0.0, 0.0, 22.0], "UnitConfigName": "DgnObj_hrl_Box8x8x2_01"}, {"HashId": 671571774, "SRTHash": -2083315373, "Translate": [-32.0, 12.0, 8.0], "UnitConfigName": "DgnObj_Hrl_BoxCover4x4_01"}, {"!Parameters": {"DropTable": "Normal", "SharpWeaponJudgeType": 0}, "HashId": 688648074, "Rotate": 1.5707963705062866, "SRTHash": -703190493, "Translate": [28.0, 0.0, 14.0], "UnitConfigName": "DgnObj_Hrl_Box4x8x12_01"}, {"!Parameters": {"DropTable": "Normal", "SharpWeaponJudgeType": 0}, "HashId": 720560426, "Rotate": [0.0, 0.0, 3.1415927410125732], "SRTHash": -189432538, "Translate": [0.0, 24.5, 26.0], "UnitConfigName": "DgnObj_Hrl_CeilingPillarA_03"}, {"!Parameters": {"DropTable": "Normal", "SharpWeaponJudgeType": 0}, "HashId": 739408204, "Rotate": -1.5707963705062866, "SRTHash": -918142347, "Translate": [24.0, 0.0, 0.0], "UnitConfigName": "DgnObj_Hrl_Box4x4x6_03"}, {"!Parameters": {"DropTable": "Normal", "SharpWeaponJudgeType": 0}, "HashId": 752915362, "SRTHash": 1150394864, "Translate": [2.0, 0.0, -16.0], "UnitConfigName": "DgnObj_Hrl_Box4x4x6Under_01"}, {"!Parameters": {"DropTable": "Normal", "SharpWeaponJudgeType": 0}, "HashId": 786941784, "Rotate": -1.5707963705062866, "SRTHash": -1582703062, "Translate": [24.0, 0.0, 4.0], "UnitConfigName": "DgnObj_Hrl_Box4x4x6_03"}, {"!Parameters": {"DropTable": "Normal", "SharpWeaponJudgeType": 0}, "HashId": 823609844, "SRTHash": -905228792, "Translate": [2.0, 6.0, -28.0], "UnitConfigName": "DgnObj_Hrl_Box4x4x2Top_01"}, {"!Parameters": {"DropTable": "Normal", "SharpWeaponJudgeType": 0}, "HashId": 837133082, "SRTHash": 1608562750, "Translate": [-2.0, 0.0, -16.5], "UnitConfigName": "DgnObj_Hrl_Box4x4x6Under_01"}, {"!Parameters": {"DropTable": "Normal", "SharpWeaponJudgeType": 0}, "HashId": 870512608, "SRTHash": 1265005366, "Translate": [0.0, 0.0, 6.0], "UnitConfigName": "DgnObj_hrl_Box8x8x2_01"}, {"HashId": 889352070, "SRTHash": 812492697, "Translate": [32.0, 12.0, -24.0], "UnitConfigName": "DgnObj_Hrl_BoxCover4x4_01"}, {"!Parameters": {"DropTable": "Normal", "SharpWeaponJudgeType": 0}, "HashId": 938987922, "SRTHash": 677356061, "Translate": [0.0, 16.5, 26.0], "UnitConfigName": "DgnObj_Hrl_CeilingPillarA_03"}, {"HashId": 1006207661, "SRTHash": -903868942, "Translate": [0.0, 2.0, 21.0], "UnitConfigName": "DgnObj_Hrl_RoadEnd4x4_01"}, {"!Parameters": {"DropTable": "Normal", "SharpWeaponJudgeType": 0}, "HashId": 1025055435, "Rotate": 1.5707963705062866, "SRTHash": -238249242, "Translate": [-24.0, 0.0, 28.0], "UnitConfigName": "DgnObj_Hrl_Box4x4x6_03"}, {"!Parameters": {"DropTable": "Normal", "SharpWeaponJudgeType": 0}, "HashId": 1034983270, "Rotate": -1.5707963705062866, "SRTHash": -189852144, "Translate": [24.0, 0.0, -16.0], "UnitConfigName": "DgnObj_Hrl_Box4x4x6_03"}, {"HashId": 1054872683, "SRTHash": -1883499043, "Translate": [-28.0, 0.0, 28.0], "UnitConfigName": "DgnObj_Hrl_Box4x4x6Center_01"}, {"!Parameters": {"DropTable": "Normal", "SharpWeaponJudgeType": 0}, "HashId": 1072473311, "OnlyOne": true, "SRTHash": -712969426, "Translate": [0.0, 6.0, -12.0], "UnitConfigName": "DgnObj_hrl_Stair4x4x2_01"}, {"!Parameters": {"DropTable": "Normal", "SharpWeaponJudgeType": 0}, "HashId": 1094295901, "Rotate": 1.5707963705062866, "SRTHash": -291682245, "Translate": [6.0, 2.0, -28.0], "UnitConfigName": "DgnObj_Hrl_Box4x4x6_03"}, {"!Parameters": {"DropTable": "Normal", "SharpWeaponJudgeType": 0}, "HashId": 1137450825, "SRTHash": 550470387, "Translate": [10.0, 2.0, 8.0], "UnitConfigName": "DgnObj_Hrl_TowerRoof4x4_A_01"}, {"!Parameters": {"DropTable": "Normal", "SharpWeaponJudgeType": 0}, "HashId": 1142962075, "Rotate": 1.5707963705062866, "SRTHash": -1004182189, "Translate": [-28.0, 0.0, 6.0], "UnitConfigName": "DgnObj_Hrl_Box4x8x12_01"}, {"!Parameters": {"DropTable": "Normal", "SharpWeaponJudgeType": 0}, "HashId": 1160546095, "Rotate": -3.1415927410125732, "SRTHash": -1030384519, "Translate": [2.0, 2.0, 32.0], "UnitConfigName": "DgnObj_Hrl_Box4x4Wainscot_01"}, {"!Parameters": {"DropTable": "Normal", "SharpWeaponJudgeType": 0}, "HashId": 1176986465, "SRTHash": -1544497140, "Translate": [2.0, 0.0, -24.0], "UnitConfigName": "DgnObj_Hrl_Box4x4x6Under_01"}, {"!Parameters": {"DropTable": "Normal", "SharpWeaponJudgeType": 0}, "HashId": 1227019280, "SRTHash": -2107611699, "Translate": [10.0, 2.0, -28.0], "UnitConfigName": "DgnObj_Hrl_TowerRoof2x2_A_01"}, {"!Parameters": {"DropTable": "Normal", "SharpWeaponJudgeType": 0}, "HashId": 1249007389, "Rotate": -1.5707963705062866, "SRTHash": 505435108, "Translate": [-6.0, 2.0, -16.0], "UnitConfigName": "DgnObj_Hrl_Box4x4x6_03"}, {"!Parameters": {"DropTable": "Normal", "SharpWeaponJudgeType": 0}, "HashId": 1255922352, "SRTHash": 2016211333, "Translate": [-28.0, 12.0, 24.0], "UnitConfigName": "DgnObj_Hrl_TowerRoof4x4_A_01"}, {"HashId": 1272408580, "Rotate": 3.1415927410125732, "SRTHash": -752963815, "Translate": [0.0, 6.0, -7.5], "UnitConfigName": "DgnObj_Hrl_RoadEnd4x4_01"}, {"!Parameters": {"DropTable": "Normal", "SharpWeaponJudgeType": 0}, "HashId": 1298961697, "SRTHash": 114262653, "Translate": [8.0, 0.0, -18.0], "UnitConfigName": "DgnObj_hrl_Box8x8x2_01"}, {"!Parameters": {"DropTable": "Normal", "SharpWeaponJudgeType": 0}, "HashId": 1302233039, "SRTHash": 473593924, "Translate": [8.0, 0.0, -10.0], "UnitConfigName": "DgnObj_hrl_Box8x8x2_01"}, {"!Parameters": {"DropTable": "Normal", "SharpWeaponJudgeType": 0}, "HashId": 1338133622, "Rotate": -1.5707963705062866, "SRTHash": -161366045, "Translate": [-4.0, 2.0, -4.0], "UnitConfigName": "DgnObj_Hrl_Box4x4x4_03"}, {"!Parameters": {"DropTable": "Normal", "SharpWeaponJudgeType": 0}, "HashId": 1345503962, "SRTHash": 1608234537, "Translate": [-28.0, 12.0, 12.0], "UnitConfigName": "DgnObj_Hrl_TowerRoof4x4_A_01"}, {"!Parameters": {"DropTable": "Normal", "SharpWeaponJudgeType": 0}, "HashId": 1349100953, "Rotate": -1.5707963705062866, "SRTHash": -1711241763, "Translate": [-6.0, 2.0, -24.0], "UnitConfigName": "DgnObj_Hrl_Box4x4x6_03"}, {"!Parameters": {"DropTable": "Normal", "SharpWeaponJudgeType": 0}, "HashId": 1352355703, "Rotate": 1.5707963705062866, "SRTHash": -1070585869, "Translate": [-24.0, 0.0, -12.0], "UnitConfigName": "DgnObj_Hrl_Box4x4x6_03"}, {"!Parameters": {"DropTable": "Normal", "SharpWeaponJudgeType": 0}, "HashId": 1388805326, "Rotate": -1.5707963705062866, "SRTHash": 38399784, "Translate": [24.0, 0.0, -4.0], "UnitConfigName": "DgnObj_Hrl_Box4x4x6_03"}, {"!Parameters": {"DropTable": "Normal", "SharpWeaponJudgeType": 0}, "HashId": 1411900584, "Rotate": -1.5707963705062866, "SRTHash": -1165560680, "Translate": [8.0, 8.0, -32.0], "UnitConfigName": "DgnObj_Hrl_Box4x4Wainscot_01"}, {"!Parameters": {"DropTable": "Normal", "SharpWeaponJudgeType": 0}, "HashId": 1557035787, "SRTHash": -1606702962, "Translate": [0.0, 0.0, 0.0], "UnitConfigName": "DgnObj_hrl_Box4x4x6_01"}, {"!Parameters": {"DropTable": "Normal", "SharpWeaponJudgeType": 0}, "HashId": 1590243313, "Rotate": -1.5707963705062866, "SRTHash": 502086275, "Translate": [24.0, 0.0, 12.0], "UnitConfigName": "DgnObj_Hrl_Box4x4x6_03"}, {"HashId": 1646515943, "SRTHash": 1397672956, "Translate": [-32.0, 12.0, 16.0], "UnitConfigName": "DgnObj_Hrl_BoxCover4x4_01"}, {"!Parameters": {"DropTable": "Normal", "SharpWeaponJudgeType": 0}, "HashId": 1664050771, "SRTHash": -2129741074, "Translate": [28.0, 12.0, 0.0], "UnitConfigName": "DgnObj_Hrl_TowerRoof4x4_A_01"}, {"HashId": 1708129845, "SRTHash": 156869482, "Translate": [-32.0, 12.0, -16.0], "UnitConfigName": "DgnObj_Hrl_BoxCover4x4_01"}, {"!Parameters": {"DropTable": "Normal", "SharpWeaponJudgeType": 0}, "HashId": 1798574878, "SRTHash": 977332335, "Translate": [8.0, 2.0, -12.0], "UnitConfigName": "DgnObj_hrl_Pillar1x1x4_01"}, {"!Parameters": {"DropTable": "Normal", "SharpWeaponJudgeType": 0}, "HashId": 1826110412, "SRTHash": -398505156, "Translate": [9.0, 2.0, -30.979999542236328], "UnitConfigName": "DgnObj_Hrl_Box2x2Wainscot_02"}, {"!Parameters": {"DropTable": "Normal", "SharpWeaponJudgeType": 0}, "HashId": 1838148667, "Rotate": 1.5707963705062866, "SRTHash": -1360528617, "Translate": [28.0, 0.0, -26.0], "UnitConfigName": "DgnObj_Hrl_Box4x8x12_01"}, {"!Parameters": {"DropTable": "Normal", "SharpWeaponJudgeType": 0}, "HashId": 1864447340, "SRTHash": -746125922, "Translate": [0.0, 0.0, -8.0], "UnitConfigName": "DgnObj_hrl_Box4x4x6_01"}, {"!Parameters": {"DropTable": "Normal", "SharpWeaponJudgeType": 0}, "HashId": 1886926445, "Rotate": 1.5707963705062866, "SRTHash": 1766366510, "Translate": [6.0, 2.0, -16.0], "UnitConfigName": "DgnObj_Hrl_Box4x4x6_03"}, {"!Parameters": {"DropTable": "Normal", "SharpWeaponJudgeType": 0}, "HashId": 1892793280, "SRTHash": -776058098, "Translate": [0.0, 0.0, 30.0], "UnitConfigName": "DgnObj_hrl_Box8x8x2_01"}, {"!Parameters": {"DropTable": "Normal", "SharpWeaponJudgeType": 0}, "HashId": 1914963412, "Rotate": -1.5707963705062866, "SRTHash": 396447001, "Translate": [-4.0, 2.0, -8.0], "UnitConfigName": "DgnObj_Hrl_Box4x4x4_03"}, {"!Parameters": {"DropTable": "Normal", "SharpWeaponJudgeType": 0}, "HashId": 1976052998, "SRTHash": -277451458, "Translate": [0.0, 0.5, -4.0], "UnitConfigName": "DgnObj_hrl_Box4x4x6_01"}, {"HashId": 1976359601, "OnlyOne": true, "Rotate": -3.1415927410125732, "SRTHash": 955776311, "Translate": [0.0, 2.0, 21.0], "UnitConfigName": "DungeonResetPosTag"}, {"!Parameters": {"DropTable": "Normal", "SharpWeaponJudgeType": 0}, "HashId": 1982931878, "SRTHash": -1874250219, "Translate": [0.0, 22.5, -24.0], "UnitConfigName": "DgnObj_Hrl_GoalSystemCenter_01"}, {"!Parameters": {"DropTable": "Normal", "SharpWeaponJudgeType": 0}, "HashId": 2003235921, "Rotate": 1.5707963705062866, "SRTHash": -1307986436, "Translate": [6.0, 2.0, -20.0], "UnitConfigName": "DgnObj_Hrl_Box4x4x6_03"}, {"HashId": 2026557069, "SRTHash": 1439352486, "Translate": [-32.0, 12.0, -24.0], "UnitConfigName": "DgnObj_Hrl_BoxCover4x4_01"}, {"!Parameters": {"DropTable": "Normal", "SharpWeaponJudgeType": 0}, "HashId": 2066989101, "Rotate": -1.5707963705062866, "SRTHash": -153302569, "Translate": [-6.0, 2.0, -28.0], "UnitConfigName": "DgnObj_Hrl_Box4x4x6_03"}, {"!Parameters": {"DropTable": "Normal", "SharpWeaponJudgeType": 0}, "HashId": 2083324433, "SRTHash": 1776452760, "Translate": [2.0, 0.0, -20.0], "UnitConfigName": "DgnObj_Hrl_Box4x4x6Under_01"}, {"!Parameters": {"DropTable": "Normal", "SharpWeaponJudgeType": 0}, "HashId": 2095048959, "SRTHash": -1978009281, "Translate": [-8.0, 0.0, -18.0], "UnitConfigName": "DgnObj_hrl_Box8x8x2_01"}, {"!Parameters": {"DropTable": "Normal", "SharpWeaponJudgeType": 0}, "HashId": 2116703979, "SRTHash": -280913101, "Translate": [-8.0, 0.0, 6.0], "UnitConfigName": "DgnObj_hrl_Box8x8x2_01"}, {"HashId": 2156640673, "SRTHash": -2050181218, "Translate": [0.0, 6.0, -0.5], "UnitConfigName": "DgnObj_Hrl_RoadEnd4x4_01"}, {"!Parameters": {"DropTable": "Normal", "SharpWeaponJudgeType": 0}, "HashId": 2167309496, "Rotate": 1.5707963705062866, "SRTHash": -1698052870, "Translate": [-24.0, 0.0, -16.0], "UnitConfigName": "DgnObj_Hrl_Box4x4x6_03"}, {"!Parameters": {"DropTable": "Normal", "SharpWeaponJudgeType": 0}, "HashId": 2189297589, "SRTHash": -1452369234, "Translate": [-10.0, 2.0, -28.0], "UnitConfigName": "DgnObj_Hrl_TowerRoof2x2_A_01"}, {"!Parameters": {"DropTable": "Normal", "SharpWeaponJudgeType": 0}, "HashId": 2224988115, "Rotate": 1.5707963705062866, "SRTHash": 1792448605, "Translate": [-28.0, 0.0, -2.0], "UnitConfigName": "DgnObj_Hrl_Box4x8x12_01"}, {"!Parameters": {"DropTable": "Normal", "SharpWeaponJudgeType": 0}, "HashId": 2251310724, "Rotate": 1.5707963705062866, "SRTHash": 1229979065, "Translate": [-24.0, 0.0, -20.0], "UnitConfigName": "DgnObj_Hrl_Box4x4x6_03"}, {"!Parameters": {"DropTable": "Normal", "SharpWeaponJudgeType": 0}, "HashId": 2255167943, "Rotate": 1.5707963705062866, "SRTHash": 701516374, "Translate": [-24.0, 0.0, 16.0], "UnitConfigName": "DgnObj_Hrl_Box4x4x6_03"}, {"!Parameters": {"DropTable": "Normal", "SharpWeaponJudgeType": 0}, "HashId": 2260905066, "Rotate": -1.5707963705062866, "SRTHash": -1487227758, "Translate": [24.0, 0.0, -12.0], "UnitConfigName": "DgnObj_Hrl_Box4x4x6_03"}, {"!Parameters": {"DropTable": "Normal", "SharpWeaponJudgeType": 0}, "HashId": 2291191020, "SRTHash": -856365542, "Translate": [-10.0, 2.0, 8.0], "UnitConfigName": "DgnObj_Hrl_TowerRoof4x4_A_01"}, {"!Parameters": {"DropTable": "Normal", "SharpWeaponJudgeType": 0}, "HashId": 2321904376, "SRTHash": 35539575, "Translate": [-8.0, 0.0, -26.0], "UnitConfigName": "DgnObj_hrl_Box8x8x2_01"}, {"!Parameters": {"DropTable": "Normal", "SharpWeaponJudgeType": 0}, "HashId": 2325190678, "SRTHash": -1906973279, "Translate": [-4.5, 8.0, -15.0], "UnitConfigName": "DgnObj_Hrl_TowerRoof2x2_A_01"}, {"!Parameters": {"DropTable": "Normal", "SharpWeaponJudgeType": 0}, "HashId": 2389726346, "Rotate": -3.1415927410125732, "SRTHash": -1662843192, "Translate": [-1.0, 2.0, 31.0], "UnitConfigName": "DgnObj_Hrl_Box2x2Wainscot_02"}, {"!Parameters": {"DropTable": "Normal", "SharpWeaponJudgeType": 0}, "HashId": 2407326782, "SRTHash": -651348918, "Translate": [-28.0, 12.0, 0.0], "UnitConfigName": "DgnObj_Hrl_TowerRoof4x4_A_01"}, {"!Parameters": {"DropTable": "Normal", "SharpWeaponJudgeType": 0}, "HashId": 2509634644, "Rotate": 1.5707963705062866, "SRTHash": 264709019, "Translate": [-24.0, 0.0, 8.0], "UnitConfigName": "DgnObj_Hrl_Box4x4x6_03"}, {"!Parameters": {"DropTable": "Normal", "SharpWeaponJudgeType": 0}, "HashId": 2577117035, "Rotate": 1.5707963705062866, "SRTHash": -1595286390, "Translate": [28.0, 0.0, -10.0], "UnitConfigName": "DgnObj_Hrl_Box4x8x12_01"}, {"!Parameters": {"DropTable": "Normal", "SharpWeaponJudgeType": 0}, "HashId": 2603972156, "SRTHash": -1695777778, "Translate": [-2.0, 6.0, -24.0], "UnitConfigName": "DgnObj_Hrl_Box4x4x2Top_01"}, {"!Parameters": {"DropTable": "Normal", "SharpWeaponJudgeType": 0}, "HashId": 2613550290, "SRTHash": -52982815, "Translate": [28.0, 12.0, -12.0], "UnitConfigName": "DgnObj_Hrl_TowerRoof4x4_A_01"}, {"!Parameters": {"DropTable": "Normal", "SharpWeaponJudgeType": 0}, "HashId": 2643364121, "SRTHash": -100443639, "Translate": [11.0, 2.0, -31.219999313354492], "UnitConfigName": "DgnObj_Hrl_Box2x2Wainscot_01"}, {"!Parameters": {"DropTable": "Normal", "SharpWeaponJudgeType": 0}, "HashId": 2675652365, "OnlyOne": true, "SRTHash": -1067609467, "Translate": [0.0, 8.0, -32.099998474121094], "UnitConfigName": "DgnObj_Hrl_Box4x4Wainscot_02"}, {"!Parameters": {"DropTable": "Normal", "SharpWeaponJudgeType": 0}, "HashId": 2691219643, "SRTHash": -1178587906, "Translate": [-8.0, 2.0, -12.0], "UnitConfigName": "DgnObj_hrl_Pillar1x1x4_01"}, {"!Parameters": {"DropTable": "Normal", "SharpWeaponJudgeType": 0}, "HashId": 2793953501, "Rotate": 1.5707963705062866, "SRTHash": -609435702, "Translate": [-24.0, 0.0, 24.0], "UnitConfigName": "DgnObj_Hrl_Box4x4x6_03"}, {"!Parameters": {"DropTable": "Normal", "SharpWeaponJudgeType": 0}, "HashId": 2798862238, "SRTHash": 32702232, "Translate": [28.0, 12.0, -24.0], "UnitConfigName": "DgnObj_Hrl_TowerRoof4x4_A_01"}, {"!Parameters": {"DropTable": "Normal", "SharpWeaponJudgeType": 0}, "HashId": 2810505321, "OnlyOne": true, "SRTHash": 1145155092, "Translate": [10.0, 0.0, -32.0], "UnitConfigName": "DgnObj_hrl_Box4x4x2_01"}, {"!Parameters": {"DropTable": "Normal", "SharpWeaponJudgeType": 0}, "HashId": 2826155510, "Rotate": 1.5707963705062866, "SRTHash": 171050473, "Translate": [4.0, 2.0, 0.0], "UnitConfigName": "DgnObj_Hrl_Box4x4x4_03"}, {"!Parameters": {"DropTable": "Normal", "SharpWeaponJudgeType": 0}, "HashId": 2843673922, "SRTHash": 1563697321, "Translate": [5.0, 4.0, -33.0], "UnitConfigName": "DgnObj_Hrl_Box2x2x4Top_01"}, {"!Parameters": {"DropTable": "Normal", "SharpWeaponJudgeType": 0}, "HashId": 2859786508, "SRTHash": -1831658010, "Translate": [3.0, 6.0, 0.0], "UnitConfigName": "DgnObj_Hrl_CandlePoleB_01"}, {"HashId": 2928881040, "SRTHash": 592125259, "Translate": [-32.0, 12.0, -8.0], "UnitConfigName": "DgnObj_Hrl_BoxCover4x4_01"}, {"!Parameters": {"DropTable": "Normal", "SharpWeaponJudgeType": 0}, "HashId": 2960069512, "Rotate": 1.5707963705062866, "SRTHash": 2047050237, "Translate": [-24.0, 0.0, -28.0], "UnitConfigName": "DgnObj_Hrl_Box4x4x6_03"}, {"HashId": 3012959528, "SRTHash": -472018153, "Translate": [32.0, 12.0, -16.0], "UnitConfigName": "DgnObj_Hrl_BoxCover4x4_01"}, {"!Parameters": {"DropTable": "Normal", "SharpWeaponJudgeType": 0}, "HashId": 3044443470, "Rotate": 1.5707963705062866, "SRTHash": -692311377, "Translate": [-24.0, 0.0, 4.0], "UnitConfigName": "DgnObj_Hrl_Box4x4x6_03"}, {"!Parameters": {"DropTable": "Normal", "SharpWeaponJudgeType": 0}, "HashId": 3077689780, "SRTHash": -1454198633, "Translate": [-2.0, 0.0, -24.0], "UnitConfigName": "DgnObj_Hrl_Box4x4x6Under_01"}, {"!Parameters": {"DropTable": "Normal", "SharpWeaponJudgeType": 0}, "HashId": 3078830938, "SRTHash": -1522330856, "Translate": [-2.0, 6.0, -28.0], "UnitConfigName": "DgnObj_Hrl_Box4x4x2Top_01"}, {"!Parameters": {"DropTable": "Normal", "SharpWeaponJudgeType": 0}, "HashId": 3111704177, "SRTHash": -1158558609, "Translate": [-8.0, 0.0, -10.0], "UnitConfigName": "DgnObj_hrl_Box8x8x2_01"}, {"!Parameters": {"DropTable": "Normal", "SharpWeaponJudgeType": 0}, "HashId": 3139757512, "Rotate": 1.5707963705062866, "SRTHash": 1854419856, "Translate": [-28.0, 0.0, -18.0], "UnitConfigName": "DgnObj_Hrl_Box4x8x12_01"}, {"!Parameters": {"DropTable": "Normal", "SharpWeaponJudgeType": 0}, "HashId": 3146606693, "SRTHash": -30488644, "Translate": [28.0, 12.0, 24.0], "UnitConfigName": "DgnObj_Hrl_TowerRoof4x4_A_01"}, {"!Parameters": {"DropTable": "Normal", "SharpWeaponJudgeType": 0}, "HashId": 3157927924, "Rotate": -1.5707963705062866, "SRTHash": 553475103, "Translate": [-6.0, 2.0, -20.0], "UnitConfigName": "DgnObj_Hrl_Box4x4x6_03"}, {"HashId": 3178098691, "OnlyOne": true, "SRTHash": 752850861, "Translate": [0.0, 25.5, -24.0], "UnitConfigName": "DgnObj_Hrl_GoalSystemTop_01"}, {"!Parameters": {"DropTable": "Normal", "SharpWeaponJudgeType": 0}, "HashId": 3197435555, "Rotate": 1.5707963705062866, "SRTHash": -486155873, "Translate": [28.0, 0.0, -2.0], "UnitConfigName": "DgnObj_Hrl_Box4x8x12_01"}, {"!Parameters": {"DropTable": "Normal", "SharpWeaponJudgeType": 0}, "HashId": 3214429719, "SRTHash": -1148954833, "Translate": [-11.0, 2.0, -31.0], "UnitConfigName": "DgnObj_Hrl_Box2x2Wainscot_01"}, {"!Parameters": {"DropTable": "Normal", "SharpWeaponJudgeType": 0}, "HashId": 3283678593, "SRTHash": 1563697321, "Translate": [5.0, 4.0, -31.0], "UnitConfigName": "DgnObj_Hrl_Box2x2x4Top_01"}, {"HashId": 3293896019, "SRTHash": 883726394, "Translate": [32.0, 12.0, 16.0], "UnitConfigName": "DgnObj_Hrl_BoxCover4x4_01"}, {"!Parameters": {"DropTable": "Normal", "SharpWeaponJudgeType": 0}, "HashId": 3310906855, "Rotate": -1.5707963705062866, "SRTHash": 1573512804, "Translate": [24.0, 0.0, 8.0], "UnitConfigName": "DgnObj_Hrl_Box4x4x6_03"}, {"!Parameters": {"DropTable": "Normal", "SharpWeaponJudgeType": 0}, "HashId": 3344906525, "SRTHash": -119235708, "Translate": [4.5, 8.0, -15.0], "UnitConfigName": "DgnObj_Hrl_TowerRoof2x2_A_01"}, {"!Parameters": {"DropTable": "Normal", "SharpWeaponJudgeType": 0}, "HashId": 3350057971, "SRTHash": 99045186, "Translate": [2.0, 0.0, -28.0], "UnitConfigName": "DgnObj_Hrl_Box4x4x6Under_01"}, {"!Parameters": {"DropTable": "Normal", "SharpWeaponJudgeType": 0}, "HashId": 3377872600, "Rotate": 1.5707963705062866, "SRTHash": -40573748, "Translate": [4.0, 2.0, -4.0], "UnitConfigName": "DgnObj_Hrl_Box4x4x4_03"}, {"HashId": 3400478840, "Rotate": 3.1415927410125732, "SRTHash": 1054731263, "Translate": [0.0, 2.0, 13.0], "UnitConfigName": "DgnObj_Hrl_RoadEnd4x4_01"}, {"!Parameters": {"DropTable": "Normal", "SharpWeaponJudgeType": 0}, "HashId": 3406433633, "SRTHash": 363979386, "Translate": [2.0, 6.0, -16.0], "UnitConfigName": "DgnObj_Hrl_Box4x4x2Top_01"}, {"!Parameters": {"DropTable": "Normal", "SharpWeaponJudgeType": 0}, "HashId": 3416490188, "Rotate": -1.5707963705062866, "SRTHash": 1955050917, "Translate": [24.0, 0.0, 16.0], "UnitConfigName": "DgnObj_Hrl_Box4x4x6_03"}, {"!Parameters": {"DropTable": "Normal", "SharpWeaponJudgeType": 0}, "HashId": 3422087055, "Rotate": -1.5707963705062866, "SRTHash": -1879426183, "Translate": [24.0, 0.0, -20.0], "UnitConfigName": "DgnObj_Hrl_Box4x4x6_03"}, {"HashId": 3443726506, "SRTHash": 282084175, "Translate": [0.0, 8.0, -16.5], "UnitConfigName": "DgnObj_Hrl_RoadEnd4x4_01"}, {"!Parameters": {"DropTable": "Normal", "SharpWeaponJudgeType": 0}, "HashId": 3484853950, "SRTHash": -629883365, "Translate": [28.0, 6.0, 28.0], "UnitConfigName": "DgnObj_Hrl_Box4x4x6Top_01"}, {"!Parameters": {"DropTable": "Normal", "SharpWeaponJudgeType": 0}, "HashId": 3507617765, "Rotate": 1.5707963705062866, "SRTHash": -767961526, "Translate": [6.0, 2.0, -24.0], "UnitConfigName": "DgnObj_Hrl_Box4x4x6_03"}, {"HashId": 3534984710, "SRTHash": -1317492167, "Translate": [32.0, 12.0, 24.0], "UnitConfigName": "DgnObj_Hrl_BoxCover4x4_01"}, {"!Parameters": {"DropTable": "Normal", "SharpWeaponJudgeType": 0}, "HashId": 3552519858, "SRTHash": -1813654462, "Translate": [-3.0, 6.0, -8.0], "UnitConfigName": "DgnObj_Hrl_CandlePoleB_01"}, {"!Parameters": {"DropTable": "Normal", "SharpWeaponJudgeType": 0}, "HashId": 3562212960, "SRTHash": -2072997639, "Translate": [8.0, 0.0, -2.0], "UnitConfigName": "DgnObj_hrl_Box8x8x2_01"}, {"!Parameters": {"DropTable": "Normal", "SharpWeaponJudgeType": 0}, "HashId": 3591323097, "Rotate": 1.5707963705062866, "SRTHash": 1749695461, "Translate": [-24.0, 0.0, -8.0], "UnitConfigName": "DgnObj_Hrl_Box4x4x6_03"}, {"!Parameters": {"DropTable": "Normal", "SharpWeaponJudgeType": 0}, "HashId": 3601248372, "Rotate": -1.5707963705062866, "SRTHash": 686032083, "Translate": [24.0, 0.0, 24.0], "UnitConfigName": "DgnObj_Hrl_Box4x4x6_03"}, {"!Parameters": {"DropTable": "Normal", "SharpWeaponJudgeType": 0}, "HashId": 3606959927, "Rotate": 1.5707963705062866, "SRTHash": 1647112657, "Translate": [-24.0, 0.0, -24.0], "UnitConfigName": "DgnObj_Hrl_Box4x4x6_03"}, {"!Parameters": {"DropTable": "Normal", "SharpWeaponJudgeType": 0}, "HashId": 3629997407, "SRTHash": 2070874839, "Translate": [0.0, 0.0, 14.0], "UnitConfigName": "DgnObj_hrl_Box8x8x2_01"}, {"!Parameters": {"DropTable": "Normal", "SharpWeaponJudgeType": 0}, "HashId": 3663333797, "Rotate": -1.5707963705062866, "SRTHash": 1212307864, "Translate": [-4.0, 2.0, 0.0], "UnitConfigName": "DgnObj_Hrl_Box4x4x4_03"}, {"!Parameters": {"DropTable": "Normal", "SharpWeaponJudgeType": 0}, "HashId": 3668501323, "Rotate": -1.5707963705062866, "SRTHash": -835755782, "Translate": [24.0, 0.0, -28.0], "UnitConfigName": "DgnObj_Hrl_Box4x4x6_03"}, {"!Parameters": {"DropTable": "Normal", "SharpWeaponJudgeType": 0}, "HashId": 3736978745, "SRTHash": 492283945, "Translate": [2.0, 6.0, -32.0], "UnitConfigName": "DgnObj_Hrl_Box4x4x2Top_01"}, {"!Parameters": {"DropTable": "Normal", "SharpWeaponJudgeType": 0}, "HashId": 3786289807, "OnlyOne": true, "SRTHash": 1847911410, "Translate": [0.0, 24.5, 26.0], "UnitConfigName": "DgnObj_Hrl_CeilingPillarA_02"}, {"!Parameters": {"DropTable": "Normal", "SharpWeaponJudgeType": 0}, "HashId": 3797367855, "Rotate": 1.5707963705062866, "SRTHash": -1642376030, "Translate": [-28.0, 0.0, 14.0], "UnitConfigName": "DgnObj_Hrl_Box4x8x12_01"}, {"HashId": 3814427803, "SRTHash": 679503879, "Translate": [-32.0, 12.0, 24.0], "UnitConfigName": "DgnObj_Hrl_BoxCover4x4_01"}, {"!Parameters": {"DropTable": "Normal", "SharpWeaponJudgeType": 0}, "HashId": 3854243069, "SRTHash": -439002403, "Translate": [8.0, 0.0, 6.0], "UnitConfigName": "DgnObj_hrl_Box8x8x2_01"}, {"!Parameters": {"DropTable": "Normal", "SharpWeaponJudgeType": 0}, "HashId": 3887874055, "SRTHash": 1671543842, "Translate": [0.0, 0.0, 2.0], "UnitConfigName": "DgnObj_hrl_Box8x8x2_01"}, {"!Parameters": {"DropTable": "Normal", "SharpWeaponJudgeType": 0}, "HashId": 3920971714, "Rotate": 1.5707963705062866, "SRTHash": -279171837, "Translate": [-28.0, 0.0, -10.0], "UnitConfigName": "DgnObj_Hrl_Box4x8x12_01"}, {"!Parameters": {"DropTable": "Normal", "SharpWeaponJudgeType": 0}, "HashId": 3944455829, "Rotate": -1.5707963705062866, "SRTHash": -18005042, "Translate": [24.0, 0.0, -24.0], "UnitConfigName": "DgnObj_Hrl_Box4x4x6_03"}, {"!Parameters": {"DropTable": "Normal", "SharpWeaponJudgeType": 0}, "HashId": 3946904022, "Rotate": 1.5707963705062866, "SRTHash": -1511370984, "Translate": [-28.0, 0.0, 22.0], "UnitConfigName": "DgnObj_Hrl_Box4x8x12_01"}, {"!Parameters": {"DropTable": "Normal", "SharpWeaponJudgeType": 0}, "HashId": 3957945467, "SRTHash": 2108283874, "Translate": [-2.0, 6.0, -20.0], "UnitConfigName": "DgnObj_Hrl_Box4x4x2Top_01"}, {"!Parameters": {"DropTable": "Normal", "SharpWeaponJudgeType": 0}, "HashId": 3959774377, "Rotate": 1.5707963705062866, "SRTHash": 632073278, "Translate": [4.0, 2.0, -12.0], "UnitConfigName": "DgnObj_Hrl_Box4x4x4_03"}, {"!Parameters": {"DropTable": "Normal", "SharpWeaponJudgeType": 0}, "HashId": 3970748676, "Rotate": 1.5707963705062866, "SRTHash": -700838495, "Translate": [28.0, 0.0, 22.0], "UnitConfigName": "DgnObj_Hrl_Box4x8x12_01"}, {"!Parameters": {"DropTable": "Normal", "SharpWeaponJudgeType": 0}, "HashId": 3986710960, "SRTHash": -831027416, "Translate": [8.0, 2.0, 1.0], "UnitConfigName": "DgnObj_hrl_Pillar1x1x4_01"}, {"HashId": 4015382436, "SRTHash": 865331230, "Translate": [-6.0, 2.0, -32.0], "UnitConfigName": "DgnObj_Hrl_BoxCover4x4_01"}, {"!Parameters": {"DropTable": "Normal", "SharpWeaponJudgeType": 0}, "HashId": 4037366024, "Rotate": [0.0, 0.0, -3.1415927410125732], "SRTHash": 243239258, "Translate": [0.0, 26.5, -24.0], "UnitConfigName": "DgnObj_Hrl_GoalSystemCenter_01"}, {"HashId": 4065390364, "SRTHash": -10591794, "Translate": [-10.0, 2.0, -32.0], "UnitConfigName": "DgnObj_Hrl_BoxCover4x4_01"}, {"!Parameters": {"DropTable": "Normal", "SharpWeaponJudgeType": 0}, "HashId": 4105205626, "Rotate": -1.5707963705062866, "SRTHash": 1399614918, "Translate": [-4.0, 2.0, -12.0], "UnitConfigName": "DgnObj_Hrl_Box4x4x4_03"}, {"!Parameters": {"DropTable": "Normal", "SharpWeaponJudgeType": 0}, "HashId": 4122789838, "SRTHash": 154341273, "Translate": [-28.0, 6.0, 28.0], "UnitConfigName": "DgnObj_Hrl_Box4x4x6Top_01"}, {"!Parameters": {"DropTable": "Normal", "SharpWeaponJudgeType": 0}, "HashId": 4131768686, "Rotate": -1.5707963705062866, "SRTHash": 1816653485, "Translate": [24.0, 0.0, 28.0], "UnitConfigName": "DgnObj_Hrl_Box4x4x6_03"}, {"!Parameters": {"DropTable": "Normal", "SharpWeaponJudgeType": 0}, "HashId": 4142679235, "Rotate": 1.5707963705062866, "SRTHash": 1027264208, "Translate": [28.0, 0.0, -18.0], "UnitConfigName": "DgnObj_Hrl_Box4x8x12_01"}, {"!Parameters": {"DropTable": "Normal", "SharpWeaponJudgeType": 0}, "HashId": 4173210693, "OnlyOne": true, "SRTHash": 1468833002, "Translate": [0.0, 2.0, 8.0], "UnitConfigName": "DgnObj_hrl_Stair8x4x4_01"}, {"!Parameters": {"DropTable": "Normal", "SharpWeaponJudgeType": 0}, "HashId": 4206457023, "SRTHash": -58150470, "Translate": [-2.0, 0.0, -20.0], "UnitConfigName": "DgnObj_Hrl_Box4x4x6Under_01"}, {"!Parameters": {"DropTable": "Normal", "SharpWeaponJudgeType": 0}, "HashId": 4239065655, "OnlyOne": true, "SRTHash": 849284493, "Translate": [0.0, 7.5, 26.0], "UnitConfigName": "DgnObj_Hrl_CeilingPillarA_01"}, {"HashId": 4267621411, "SRTHash": 348219920, "Translate": [32.0, 12.0, -8.0], "UnitConfigName": "DgnObj_Hrl_BoxCover4x4_01"}], "Rails": []}